pygments_woma_lexer/__init__.py
pygments_woma_lexer/main.py
pygments_woma_lexer-1.0.9.dist-info/LICENSE.txt
pygments_woma_lexer-1.0.9.dist-info/METADATA
pygments_woma_lexer-1.0.9.dist-info/WHEEL
pygments_woma_lexer-1.0.9.dist-info/top_level.txt
pygments_woma_lexer-1.0.9.dist-info/RECORD
