Metadata-Version: 2.1
Name: pygments-woma-lexer
Version: 1.0.9
Summary: A pygments lexer for the Woma Programming Language
Home-page: https://github.com/rjdbcm/pygments_woma_lexer
Author: Ross J. Duff
Author-email: rjdbcm@mail.umkc.edu
License: MIT
Keywords: lexer
Platform: UNKNOWN
Classifier: Operating System :: POSIX :: Linux
Classifier: Operating System :: MacOS :: MacOS X
Classifier: Operating System :: Microsoft :: Windows
Classifier: Development Status :: 3 - Alpha
Classifier: Environment :: Console
Classifier: Programming Language :: Other
Classifier: Programming Language :: Python :: 3.7
Classifier: Programming Language :: Python :: 3.8
Classifier: Programming Language :: Python :: 3.9
Classifier: Programming Language :: Python :: Implementation :: CPython
Classifier: Topic :: Utilities
Classifier: License :: OSI Approved :: MIT License
License-File: LICENSE.txt
Requires-Dist: pygments (>=2.10.0)
